organelle_segmenter_plugin/__init__.py
organelle_segmenter_plugin/_dock_widget.py
organelle_segmenter_plugin/_reader.py
organelle_segmenter_plugin/_style.py
organelle_segmenter_plugin/_version.py
organelle_segmenter_plugin/napari.yaml
organelle_segmenter_plugin/_tests/__init__.py
organelle_segmenter_plugin/_tests/conftest.py
organelle_segmenter_plugin/_tests/mocks.py
organelle_segmenter_plugin/_tests/style_test.py
organelle_segmenter_plugin/_tests/controller/__init__.py
organelle_segmenter_plugin/_tests/controller/batch_processing_controller_test.py
organelle_segmenter_plugin/_tests/controller/workflow_select_controller_test.py
organelle_segmenter_plugin/_tests/controller/workflow_steps_controller_test.py
organelle_segmenter_plugin/_tests/core/__init__.py
organelle_segmenter_plugin/_tests/core/application_test.py
organelle_segmenter_plugin/_tests/core/controller_test.py
organelle_segmenter_plugin/_tests/core/layer_reader_test.py
organelle_segmenter_plugin/_tests/core/router_test.py
organelle_segmenter_plugin/_tests/core/state_test.py
organelle_segmenter_plugin/_tests/core/view_manager_test.py
organelle_segmenter_plugin/_tests/core/view_test.py
organelle_segmenter_plugin/_tests/core/viewer_abstraction_test.py
organelle_segmenter_plugin/_tests/model/__init__.py
organelle_segmenter_plugin/_tests/model/segmenter_model_test.py
organelle_segmenter_plugin/_tests/util/__init__.py
organelle_segmenter_plugin/_tests/util/convert_test.py
organelle_segmenter_plugin/_tests/util/lazy_test.py
organelle_segmenter_plugin/_tests/view/__init__.py
organelle_segmenter_plugin/_tests/view/_main_template_test.py
organelle_segmenter_plugin/_tests/view/batch_processing_view_test.py
organelle_segmenter_plugin/_tests/view/workflow_select_view_test.py
organelle_segmenter_plugin/_tests/view/workflow_steps_view_test.py
organelle_segmenter_plugin/_tests/widgets/__init__.py
organelle_segmenter_plugin/_tests/widgets/collapsible_box_test.py
organelle_segmenter_plugin/_tests/widgets/file_input_test.py
organelle_segmenter_plugin-0.0.6.dist-info/LICENSE
organelle_segmenter_plugin-0.0.6.dist-info/METADATA
organelle_segmenter_plugin-0.0.6.dist-info/WHEEL
organelle_segmenter_plugin-0.0.6.dist-info/entry_points.txt
organelle_segmenter_plugin-0.0.6.dist-info/top_level.txt
organelle_segmenter_plugin-0.0.6.dist-info/RECORD
