Metadata-Version: 2.1
Name: organelle-segmenter-plugin
Version: 0.0.6
Summary: A plugin that enables organelle segmentation, forked from tools from Allen Institute for Cell Science
Home-page: https://github.com/ndcn/organelle-segmenter-plugin
Author: Andy Henrie
Author-email: ergonyc@gmail.com
License: BSD-3
Project-URL: Bug Tracker, https://github.com/ndcn/organelle-segmenter-plugin/issues
Project-URL: Documentation, https://github.com/ndcn/organelle-segmenter-plugin#README.md
Project-URL: Source Code, https://github.com/ndcn/organelle-segmenter-plugin
Project-URL: User Support, https://github.com/ndcn/organelle-segmenter-plugin/issues
Classifier: Development Status :: 3 - Alpha
Classifier: Intended Audience :: Science/Research
Classifier: Framework :: napari
Classifier: Topic :: Scientific/Engineering
Classifier: Topic :: Scientific/Engineering :: Visualization
Classifier: Topic :: Scientific/Engineering :: Information Analysis
Classifier: Topic :: Scientific/Engineering :: Bio-Informatics
Classifier: Programming Language :: Python
Classifier: Programming Language :: Python :: 3
Classifier: Programming Language :: Python :: 3.8
Classifier: Programming Language :: Python :: 3.9
Classifier: Programming Language :: Python :: 3.10
Classifier: Operating System :: OS Independent
Classifier: License :: OSI Approved :: BSD License
Requires-Python: >=3.8
License-File: LICENSE
Requires-Dist: napari
Requires-Dist: napari-plugin-engine>=0.1.4
Requires-Dist: aicssegmentation
Requires-Dist: aicsimageio
Requires-Dist: numpy
Requires-Dist: scikit-image
Requires-Dist: aicsimageio>=4.7.0
Provides-Extra: testing
Requires-Dist: tox; extra == "testing"
Requires-Dist: pytest; extra == "testing"
Requires-Dist: pytest-cov; extra == "testing"
Requires-Dist: pytest-qt; extra == "testing"
Requires-Dist: napari; extra == "testing"
Requires-Dist: pyqt5; extra == "testing"
